fastly_cli-0.1.3.dist-info/DESCRIPTION.rst
fastly_cli-0.1.3.dist-info/METADATA
fastly_cli-0.1.3.dist-info/RECORD
fastly_cli-0.1.3.dist-info/WHEEL
fastly_cli-0.1.3.dist-info/entry_points.txt
fastly_cli-0.1.3.dist-info/metadata.json
fastly_cli-0.1.3.dist-info/top_level.txt
fastlycli/__init__.py
fastlycli/__main__.py
fastlycli/dynamic_servers.py
fastlycli/image_optimization.py
fastlycli/remote_logging.py
fastlycli/settings.py
fastlycli/utilities.py
fastlycli/vcl.py
fastlycli/version.py
fastlycli/waf.py
fastlycli/helpers/__init__.py
fastlycli/helpers/helper.py
