Metadata-Version: 2.0
Name: fastly-cli
Version: 0.1.3
Summary: Universal command line interface for Fastly CDN
Home-page: https://github.com/mertsaygi/fastly-cli
Author: Mert Saygı
Author-email: mertsaygi@gmail.com
License: MIT
Platform: UNKNOWN
Classifier: Programming Language :: Python
Classifier: Programming Language :: Python :: 2.7
Requires-Dist: Click
Requires-Dist: requests
Requires-Dist: fastly
